redshift_auth/__init__.py
redshift_auth/redshift_auth.py
5x_redshift_auth_manager-0.1.0.dist-info/METADATA
5x_redshift_auth_manager-0.1.0.dist-info/WHEEL
5x_redshift_auth_manager-0.1.0.dist-info/top_level.txt
5x_redshift_auth_manager-0.1.0.dist-info/RECORD
